pymonkey.py
pymonkey-0.3.1.dist-info/LICENSE
pymonkey-0.3.1.dist-info/METADATA
pymonkey-0.3.1.dist-info/WHEEL
pymonkey-0.3.1.dist-info/entry_points.txt
pymonkey-0.3.1.dist-info/top_level.txt
pymonkey-0.3.1.dist-info/RECORD
